MailCraft/__init__.py
MailCraft/main.py
mailcraft-0.0.2.dist-info/METADATA
mailcraft-0.0.2.dist-info/WHEEL
mailcraft-0.0.2.dist-info/licenses/LICENSE
mailcraft-0.0.2.dist-info/RECORD
